Workbook

Sheet Demanda
A1: FASE 3 — ESTUDIO DE MERCADO: DEMANDA, OFERTA Y DEMANDA INSATISFECHA
B2: Año base (último año histórico disponible): | C2: 2023 | E2: ℹ Cambia solo esta celda → todos los encabezados de año se actualizan automáticamente
B3: ◄ DATOS HISTÓRICOS (Año 1 – Año 5) | H3: ► PROYECCIÓN DEL PROYECTO (Año 6 – Año 10)
B5: 1. PARÁMETROS DE SEGMENTACIÓN (completar celdas amarillas — un único valor por parámetro)
B6: Población de la ciudad (año base) | M6: Dato INE — proyección intercensal
B7: % Población rango etario objetivo | M7: Ej: 18-70 años → 58.97%
B8: % Extracto económico objetivo (ABC1 / NSE) | M8: Ej: estrato medio-alto → 21%
B9: % Que consume el producto/servicio | M9: Dato de encuesta (P5 aceptación) → ej: 89.84%
B10: % Con ingreso suficiente (filtro compra) | M10: Dato encuesta (P11 ingreso) → ej: 48.44%
B11: Frecuencia de compra (veces / año) | M11: Dato encuesta (P8) → ej: 60.35
B12: Consumo per cápita (productos / visita) | M12: Dato encuesta → ej: 2.27
B14: 2. DEMANDA HISTÓRICA (ingresar los valores de los 5 años anteriores al inicio del proyecto)
B15: Detalle | C15: ="Año 1 ("&TEXT($C$2+(-4),"0")&")" | D15: ="Año 2 ("&TEXT($C$2+(-3),"0")&")" | E15: ="Año 3 ("&TEXT($C$2+(-2),"0")&")" | F15: ="Año 4 ("&TEXT($C$2+(-1),"0")&")" | G15: ="Año 5 ("&TEXT($C$2+(0),"0")&")" | H15: ="Año 6 ("&TEXT($C$2+(1),"0")&")" | I15: ="Año 7 ("&TEXT($C$2+(2),"0")&")" | J15: ="Año 8 ("&TEXT($C$2+(3),"0")&")" | K15: ="Año 9 ("&TEXT($C$2+(4),"0")&")" | L15: ="Año 10 ("&TEXT($C$2+(5),"0")&")" | M15: Observaciones
B16: Demanda histórica (unidades / productos) | M16: Ingresar dato de consumo (INE, encuesta, gremio, etc.)
B17: Tasa de crecimiento interanual | D17: =IFERROR(D16/C16-1,"") | E17: =IFERROR(E16/D16-1,"") | F17: =IFERROR(F16/E16-1,"") | G17: =IFERROR(G16/F16-1,"") | M17: Calculado automáticamente
B19: 2b. REGRESIÓN LINEAL Y = a + bX (proyecta la demanda histórica hacia Año 6–10)
B20: Concepto | C20: Xi valor | D20: Año 1 | E20: Año 2 | F20: Año 3 | G20: Año 4 | H20: Año 5 | I20: Año 6 | J20: Año 7 | K20: Año 8 | L20: Año 9 | M20: Año 10
B21: Xi (período correlativo) | C21: 1 | D21: 2 | E21: 3 | F21: 4 | G21: 5 | H21: 6 | I21: 7 | J21: 8 | K21: 9 | L21: 10
B22: Yi (demanda histórica) | C22: =C16 | D22: =D16 | E22: =E16 | F22: =F16 | G22: =G16 | H22: =IFERROR(ROUND($C$24+$C$23*6,0),0) | I22: =IFERROR(ROUND($C$24+$C$23*7,0),0) | J22: =IFERROR(ROUND($C$24+$C$23*8,0),0) | K22: =IFERROR(ROUND($C$24+$C$23*9,0),0) | L22: =IFERROR(ROUND($C$24+$C$23*10,0),0)
B23: Pendiente b = | C23: =IFERROR(SLOPE(C22:G22,C21:G21),0)
B24: Intercepto a = | C24: =IFERROR(INTERCEPT(C22:G22,C21:G21),0)
B26: 3. CÁLCULO ESCALONADO — DEMANDA POTENCIAL → DISPONIBLE → EFECTIVA (proyección Año 6–10)
B27: Detalle | C27: Parámetro | H27: ="Año 6 ("&TEXT($C$2+(1),"0")&")" | I27: ="Año 7 ("&TEXT($C$2+(2),"0")&")" | J27: ="Año 8 ("&TEXT($C$2+(3),"0")&")" | K27: ="Año 9 ("&TEXT($C$2+(4),"0")&")" | L27: ="Año 10 ("&TEXT($C$2+(5),"0")&")" | M27: Observaciones
B28: Tasa de crecimiento población (%/año) | C28: 0.02 | M28: Dato INE — tasa intercensal promedio
B29: Población ciudad (proyectada) | C29: =C6 | H29: =IFERROR(ROUND(C29*(1+$C$28)^1,0),0) | I29: =IFERROR(ROUND(C29*(1+$C$28)^2,0),0) | J29: =IFERROR(ROUND(C29*(1+$C$28)^3,0),0) | K29: =IFERROR(ROUND(C29*(1+$C$28)^4,0),0) | L29: =IFERROR(ROUND(C29*(1+$C$28)^5,0),0) | M29: Pob. año base × (1+tasa)ⁿ
B30: × % Rango etario objetivo | C30: =C7 | H30: =$C$7 | I30: =$C$7 | J30: =$C$7 | K30: =$C$7 | L30: =$C$7 | M30: =C$7
B31: ▶ POBLACIÓN POTENCIAL | C31: =C31 | H31: =ROUND(H29*$C$7,0) | I31: =ROUND(I29*$C$7,0) | J31: =ROUND(J29*$C$7,0) | K31: =ROUND(K29*$C$7,0) | L31: =ROUND(L29*$C$7,0) | M31: Pob. ciudad × % etario
B32: × % Extracto económico (ABC1) | C32: =C8 | H32: =$C$8 | I32: =$C$8 | J32: =$C$8 | K32: =$C$8 | L32: =$C$8 | M32: =C$8
B33: ▶ POBLACIÓN DISPONIBLE | C33: =C33 | H33: =ROUND(H31*$C$8,0) | I33: =ROUND(I31*$C$8,0) | J33: =ROUND(J31*$C$8,0) | K33: =ROUND(K31*$C$8,0) | L33: =ROUND(L31*$C$8,0) | M33: Pob. potencial × % ABC1
B34: × % Que consume el producto | C34: =C9 | H34: =$C$9 | I34: =$C$9 | J34: =$C$9 | K34: =$C$9 | L34: =$C$9 | M34: =C$9
B35: × % Con ingreso suficiente | C35: =C10 | H35: =$C$10 | I35: =$C$10 | J35: =$C$10 | K35: =$C$10 | L35: =$C$10 | M35: =C$10
B36: ▶ POBLACIÓN EFECTIVA | C36: =C36 | H36: =ROUND(H33*$C$9*$C$10,0) | I36: =ROUND(I33*$C$9*$C$10,0) | J36: =ROUND(J33*$C$9*$C$10,0) | K36: =ROUND(K33*$C$9*$C$10,0) | L36: =ROUND(L33*$C$9*$C$10,0) | M36: Pob. disp × % consume × % ingreso
B37: × Demanda per cápita (frec × cons) | C37: =C11*C12 | H37: =$C$11*$C$12 | I37: =$C$11*$C$12 | J37: =$C$11*$C$12 | K37: =$C$11*$C$12 | L37: =$C$11*$C$12 | M37: =C$11*C$12
B38: ▶ DEMANDA EFECTIVA (productos/año) | H38: =ROUND(H36*$C$11*$C$12,0) | I38: =ROUND(I36*$C$11*$C$12,0) | J38: =ROUND(J36*$C$11*$C$12,0) | K38: =ROUND(K36*$C$11*$C$12,0) | L38: =ROUND(L36*$C$11*$C$12,0) | M38: Pob. efectiva × frec × consumo
B40: 4. OFERTA HISTÓRICA (5 años) Y OFERTA PROYECTADA (Año 6–10)
B41: Detalle | C41: ="Año 1 ("&TEXT($C$2+(-4),"0")&")" | D41: ="Año 2 ("&TEXT($C$2+(-3),"0")&")" | E41: ="Año 3 ("&TEXT($C$2+(-2),"0")&")" | F41: ="Año 4 ("&TEXT($C$2+(-1),"0")&")" | G41: ="Año 5 ("&TEXT($C$2+(0),"0")&")" | H41: ="Año 6 ("&TEXT($C$2+(1),"0")&")" | I41: ="Año 7 ("&TEXT($C$2+(2),"0")&")" | J41: ="Año 8 ("&TEXT($C$2+(3),"0")&")" | K41: ="Año 9 ("&TEXT($C$2+(4),"0")&")" | L41: ="Año 10 ("&TEXT($C$2+(5),"0")&")" | M41: Observaciones
B42: Oferta histórica (unidades) | M42: Datos de oferta del sector (INE, encuestas, visitas a competidores)
B43: Tasa de crecimiento oferta (%/año) | C43: 0.025 | M43: Estimado sectorial — puede diferir de la demanda
B44: Oferta proyectada Año 6 – Año 10 | C44: Oferta proyectada Año 6–10 | H44: ="Año 6 ("&TEXT($C$2+(1),"0")&")" | I44: ="Año 7 ("&TEXT($C$2+(2),"0")&")" | J44: ="Año 8 ("&TEXT($C$2+(3),"0")&")" | K44: ="Año 9 ("&TEXT($C$2+(4),"0")&")" | L44: ="Año 10 ("&TEXT($C$2+(5),"0")&")" | M44: Observaciones
B45: Oferta Proyectada | H45: =IFERROR(ROUND(G42*(1+$C$43),0),0) | I45: =IFERROR(ROUND(H45*(1+$C$43),0),0) | J45: =IFERROR(ROUND(I45*(1+$C$43),0),0) | K45: =IFERROR(ROUND(J45*(1+$C$43),0),0) | L45: =IFERROR(ROUND(K45*(1+$C$43),0),0) | M45: Proyectada desde Año 5 histórico con tasa oferta
B47: 5. BALANCE OFERTA – DEMANDA (DEMANDA INSATISFECHA) Año 6–10
B48: Detalle | C48: Parámetro | H48: ="Año 6 ("&TEXT($C$2+(1),"0")&")" | I48: ="Año 7 ("&TEXT($C$2+(2),"0")&")" | J48: ="Año 8 ("&TEXT($C$2+(3),"0")&")" | K48: ="Año 9 ("&TEXT($C$2+(4),"0")&")" | L48: ="Año 10 ("&TEXT($C$2+(5),"0")&")" | M48: Observaciones
B49: Demanda Efectiva Proyectada | H49: =H38 | I49: =I38 | J49: =J38 | K49: =K38 | L49: =L38
B50: Oferta Proyectada | H50: =H45 | I50: =I45 | J50: =J45 | K50: =K45 | L50: =L45
B51: ▶ DEMANDA INSATISFECHA | H51: =IFERROR(H49-H50,0) | I51: =IFERROR(I49-I50,0) | J51: =IFERROR(J49-J50,0) | K51: =IFERROR(K49-K50,0) | L51: =IFERROR(L49-L50,0)
B52: % Satisfecho (dato encuesta) | H52: =$C$52 | I52: =$C$52 | J52: =$C$52 | K52: =$C$52 | L52: =$C$52 | M52: Dato encuesta P13 satisfacción oferta actual
B53: % Insatisfecho (complemento) | C53: =IFERROR(1-$C$52,0) | H53: =IFERROR(1-$C$52,0) | I53: =IFERROR(1-$C$52,0) | J53: =IFERROR(1-$C$52,0) | K53: =IFERROR(1-$C$52,0) | L53: =IFERROR(1-$C$52,0) | M53: Complemento automático
B55: 6. PARTICIPACIÓN DE MERCADO Y DEMANDA OBJETIVO Año 6–10
B56: Detalle | C56: Parámetro | H56: ="Año 6 ("&TEXT($C$2+(1),"0")&")" | I56: ="Año 7 ("&TEXT($C$2+(2),"0")&")" | J56: ="Año 8 ("&TEXT($C$2+(3),"0")&")" | K56: ="Año 9 ("&TEXT($C$2+(4),"0")&")" | L56: ="Año 10 ("&TEXT($C$2+(5),"0")&")" | M56: Observaciones
B57: % Captación de la Demanda Insatisfecha | H57: =$C$57 | I57: =IFERROR($C$57*(1+$C$58)^1,0) | J57: =IFERROR($C$57*(1+$C$58)^2,0) | K57: =IFERROR($C$57*(1+$C$58)^3,0) | L57: =IFERROR($C$57*(1+$C$58)^4,0) | M57: Participación objetivo (ej: 0.33%)
B58: Incremento anual del % captación | H58: 0 | I58: =IFERROR((1+$C$58)^1-1,0) | J58: =IFERROR((1+$C$58)^2-1,0) | K58: =IFERROR((1+$C$58)^3-1,0) | L58: =IFERROR((1+$C$58)^4-1,0) | M58: Ej: 5% de crecimiento anual del % captación (dejar en 0 si constante)
B59: ▶ DEMANDA OBJETIVO TOTAL (productos/año) | H59: =IFERROR(ROUND(H51*($C$57),0),0) | I59: =IFERROR(ROUND(I51*($C$57*(1+$C$58)^1),0),0) | J59: =IFERROR(ROUND(J51*($C$57*(1+$C$58)^2),0),0) | K59: =IFERROR(ROUND(K51*($C$57*(1+$C$58)^3),0),0) | L59: =IFERROR(ROUND(L51*($C$57*(1+$C$58)^4),0),0) | M59: DI × %captación × (1+crec)^n
B61: 7. DISTRIBUCIÓN DEMANDA OBJETIVO POR PRODUCTO/SERVICIO (1–10 ítems) Año 6–10
B62: Producto / Servicio | C62: % Partic. | H62: ="Año 6 ("&TEXT($C$2+(1),"0")&")" | I62: ="Año 7 ("&TEXT($C$2+(2),"0")&")" | J62: ="Año 8 ("&TEXT($C$2+(3),"0")&")" | K62: ="Año 9 ("&TEXT($C$2+(4),"0")&")" | L62: ="Año 10 ("&TEXT($C$2+(5),"0")&")"
B63: DEMANDA OBJETIVO (referencia por año) | C63: 100% | H63: =H59 | I63: =I59 | J63: =J59 | K63: =K59 | L63: =L59
B64: Producto 1 | H64: =IFERROR(ROUND(H59*C64,0),0) | I64: =IFERROR(ROUND(I59*C64,0),0) | J64: =IFERROR(ROUND(J59*C64,0),0) | K64: =IFERROR(ROUND(K59*C64,0),0) | L64: =IFERROR(ROUND(L59*C64,0),0)
B65: Producto 2 | H65: =IFERROR(ROUND(H59*C65,0),0) | I65: =IFERROR(ROUND(I59*C65,0),0) | J65: =IFERROR(ROUND(J59*C65,0),0) | K65: =IFERROR(ROUND(K59*C65,0),0) | L65: =IFERROR(ROUND(L59*C65,0),0)
B66: Producto 3 | H66: =IFERROR(ROUND(H59*C66,0),0) | I66: =IFERROR(ROUND(I59*C66,0),0) | J66: =IFERROR(ROUND(J59*C66,0),0) | K66: =IFERROR(ROUND(K59*C66,0),0) | L66: =IFERROR(ROUND(L59*C66,0),0)
B67: Producto 4 | H67: =IFERROR(ROUND(H59*C67,0),0) | I67: =IFERROR(ROUND(I59*C67,0),0) | J67: =IFERROR(ROUND(J59*C67,0),0) | K67: =IFERROR(ROUND(K59*C67,0),0) | L67: =IFERROR(ROUND(L59*C67,0),0)
B68: Producto 5 | H68: =IFERROR(ROUND(H59*C68,0),0) | I68: =IFERROR(ROUND(I59*C68,0),0) | J68: =IFERROR(ROUND(J59*C68,0),0) | K68: =IFERROR(ROUND(K59*C68,0),0) | L68: =IFERROR(ROUND(L59*C68,0),0)
B69: Producto 6 | H69: =IFERROR(ROUND(H59*C69,0),0) | I69: =IFERROR(ROUND(I59*C69,0),0) | J69: =IFERROR(ROUND(J59*C69,0),0) | K69: =IFERROR(ROUND(K59*C69,0),0) | L69: =IFERROR(ROUND(L59*C69,0),0)
B70: Producto 7 | H70: =IFERROR(ROUND(H59*C70,0),0) | I70: =IFERROR(ROUND(I59*C70,0),0) | J70: =IFERROR(ROUND(J59*C70,0),0) | K70: =IFERROR(ROUND(K59*C70,0),0) | L70: =IFERROR(ROUND(L59*C70,0),0)
B71: Producto 8 | H71: =IFERROR(ROUND(H59*C71,0),0) | I71: =IFERROR(ROUND(I59*C71,0),0) | J71: =IFERROR(ROUND(J59*C71,0),0) | K71: =IFERROR(ROUND(K59*C71,0),0) | L71: =IFERROR(ROUND(L59*C71,0),0)
B72: Producto 9 | H72: =IFERROR(ROUND(H59*C72,0),0) | I72: =IFERROR(ROUND(I59*C72,0),0) | J72: =IFERROR(ROUND(J59*C72,0),0) | K72: =IFERROR(ROUND(K59*C72,0),0) | L72: =IFERROR(ROUND(L59*C72,0),0)
B73: Producto 10 | H73: =IFERROR(ROUND(H59*C73,0),0) | I73: =IFERROR(ROUND(I59*C73,0),0) | J73: =IFERROR(ROUND(J59*C73,0),0) | K73: =IFERROR(ROUND(K59*C73,0),0) | L73: =IFERROR(ROUND(L59*C73,0),0)
B74: TOTAL | C74: =IFERROR(SUM(C64:C73),0) | H74: =IFERROR(SUM(H64:H73),0) | I74: =IFERROR(SUM(I64:I73),0) | J74: =IFERROR(SUM(J64:J73),0) | K74: =IFERROR(SUM(K64:K73),0) | L74: =IFERROR(SUM(L64:L73),0)
B75: ⚠ Suma de participaciones debe ser exactamente 100% | C75: =IF(ABS(C74-1)<0.0005,"✔ OK — suma 100%","✘ REVISAR — no suma 100%")
B77: LEYENDA: 🟡 Amarillo = INPUT del usuario 🟢 Verde = resultado calculado 🟠 Dorado = Demanda Objetivo ⬛ Gris = columna no aplica

Sheet Precios
A1: FASE 3 — PRECIOS: PRECIO DE VENTA, PRECIO FACTURADO E INGRESO BRUTO (Año 6–10)
B2: ◄ PRECIO BASE (Año 5 = año de inicio del proyecto) | H2: ► PROYECCIÓN (Año 6 – Año 10)
B3: Inflación / incremento anual de precios: | C3: 0.019 | E3: Tasa inflación anual (IPC — dato INE o ASFI)
B4: Factor impositivo IT + IVA: | C4: 1.149 | E4: 1.149 = IT 3% + IVA 13% | Solo IVA: 1.13 | Sin impuesto: 1.00
B6: A. PRECIO DE VENTA (sin impuestos, Bs)
B7: Producto / Servicio | C7: Precio Año 5 (Bs) | G7: Precio base (Año 5) | H7: ="Año 6 ("&TEXT(Demanda!$C$2+(1),"0")&")" | I7: ="Año 7 ("&TEXT(Demanda!$C$2+(2),"0")&")" | J7: ="Año 8 ("&TEXT(Demanda!$C$2+(3),"0")&")" | K7: ="Año 9 ("&TEXT(Demanda!$C$2+(4),"0")&")" | L7: ="Año 10 ("&TEXT(Demanda!$C$2+(5),"0")&")" | M7: Notas
B8: =IF(Demanda!B64="","—",Demanda!B64) | H8: =IFERROR(IF(G8="","",ROUND(G8*(1+$C$3)^1,2)),"") | I8: =IFERROR(IF(G8="","",ROUND(G8*(1+$C$3)^2,2)),"") | J8: =IFERROR(IF(G8="","",ROUND(G8*(1+$C$3)^3,2)),"") | K8: =IFERROR(IF(G8="","",ROUND(G8*(1+$C$3)^4,2)),"") | L8: =IFERROR(IF(G8="","",ROUND(G8*(1+$C$3)^5,2)),"")
B9: =IF(Demanda!B65="","—",Demanda!B65) | H9: =IFERROR(IF(G9="","",ROUND(G9*(1+$C$3)^1,2)),"") | I9: =IFERROR(IF(G9="","",ROUND(G9*(1+$C$3)^2,2)),"") | J9: =IFERROR(IF(G9="","",ROUND(G9*(1+$C$3)^3,2)),"") | K9: =IFERROR(IF(G9="","",ROUND(G9*(1+$C$3)^4,2)),"") | L9: =IFERROR(IF(G9="","",ROUND(G9*(1+$C$3)^5,2)),"")
B10: =IF(Demanda!B66="","—",Demanda!B66) | H10: =IFERROR(IF(G10="","",ROUND(G10*(1+$C$3)^1,2)),"") | I10: =IFERROR(IF(G10="","",ROUND(G10*(1+$C$3)^2,2)),"") | J10: =IFERROR(IF(G10="","",ROUND(G10*(1+$C$3)^3,2)),"") | K10: =IFERROR(IF(G10="","",ROUND(G10*(1+$C$3)^4,2)),"") | L10: =IFERROR(IF(G10="","",ROUND(G10*(1+$C$3)^5,2)),"")
B11: =IF(Demanda!B67="","—",Demanda!B67) | H11: =IFERROR(IF(G11="","",ROUND(G11*(1+$C$3)^1,2)),"") | I11: =IFERROR(IF(G11="","",ROUND(G11*(1+$C$3)^2,2)),"") | J11: =IFERROR(IF(G11="","",ROUND(G11*(1+$C$3)^3,2)),"") | K11: =IFERROR(IF(G11="","",ROUND(G11*(1+$C$3)^4,2)),"") | L11: =IFERROR(IF(G11="","",ROUND(G11*(1+$C$3)^5,2)),"")
B12: =IF(Demanda!B68="","—",Demanda!B68) | H12: =IFERROR(IF(G12="","",ROUND(G12*(1+$C$3)^1,2)),"") | I12: =IFERROR(IF(G12="","",ROUND(G12*(1+$C$3)^2,2)),"") | J12: =IFERROR(IF(G12="","",ROUND(G12*(1+$C$3)^3,2)),"") | K12: =IFERROR(IF(G12="","",ROUND(G12*(1+$C$3)^4,2)),"") | L12: =IFERROR(IF(G12="","",ROUND(G12*(1+$C$3)^5,2)),"")
B13: =IF(Demanda!B69="","—",Demanda!B69) | H13: =IFERROR(IF(G13="","",ROUND(G13*(1+$C$3)^1,2)),"") | I13: =IFERROR(IF(G13="","",ROUND(G13*(1+$C$3)^2,2)),"") | J13: =IFERROR(IF(G13="","",ROUND(G13*(1+$C$3)^3,2)),"") | K13: =IFERROR(IF(G13="","",ROUND(G13*(1+$C$3)^4,2)),"") | L13: =IFERROR(IF(G13="","",ROUND(G13*(1+$C$3)^5,2)),"")
B14: =IF(Demanda!B70="","—",Demanda!B70) | H14: =IFERROR(IF(G14="","",ROUND(G14*(1+$C$3)^1,2)),"") | I14: =IFERROR(IF(G14="","",ROUND(G14*(1+$C$3)^2,2)),"") | J14: =IFERROR(IF(G14="","",ROUND(G14*(1+$C$3)^3,2)),"") | K14: =IFERROR(IF(G14="","",ROUND(G14*(1+$C$3)^4,2)),"") | L14: =IFERROR(IF(G14="","",ROUND(G14*(1+$C$3)^5,2)),"")
B15: =IF(Demanda!B71="","—",Demanda!B71) | H15: =IFERROR(IF(G15="","",ROUND(G15*(1+$C$3)^1,2)),"") | I15: =IFERROR(IF(G15="","",ROUND(G15*(1+$C$3)^2,2)),"") | J15: =IFERROR(IF(G15="","",ROUND(G15*(1+$C$3)^3,2)),"") | K15: =IFERROR(IF(G15="","",ROUND(G15*(1+$C$3)^4,2)),"") | L15: =IFERROR(IF(G15="","",ROUND(G15*(1+$C$3)^5,2)),"")
B16: =IF(Demanda!B72="","—",Demanda!B72) | H16: =IFERROR(IF(G16="","",ROUND(G16*(1+$C$3)^1,2)),"") | I16: =IFERROR(IF(G16="","",ROUND(G16*(1+$C$3)^2,2)),"") | J16: =IFERROR(IF(G16="","",ROUND(G16*(1+$C$3)^3,2)),"") | K16: =IFERROR(IF(G16="","",ROUND(G16*(1+$C$3)^4,2)),"") | L16: =IFERROR(IF(G16="","",ROUND(G16*(1+$C$3)^5,2)),"")
B17: =IF(Demanda!B73="","—",Demanda!B73) | H17: =IFERROR(IF(G17="","",ROUND(G17*(1+$C$3)^1,2)),"") | I17: =IFERROR(IF(G17="","",ROUND(G17*(1+$C$3)^2,2)),"") | J17: =IFERROR(IF(G17="","",ROUND(G17*(1+$C$3)^3,2)),"") | K17: =IFERROR(IF(G17="","",ROUND(G17*(1+$C$3)^4,2)),"") | L17: =IFERROR(IF(G17="","",ROUND(G17*(1+$C$3)^5,2)),"")
B19: B. PRECIO FACTURADO (con IT + IVA → precio al consumidor, Bs)
B20: Producto / Servicio | C20: Año 5 (base) | G20: Año 5 | H20: ="Año 6 ("&TEXT(Demanda!$C$2+(1),"0")&")" | I20: ="Año 7 ("&TEXT(Demanda!$C$2+(2),"0")&")" | J20: ="Año 8 ("&TEXT(Demanda!$C$2+(3),"0")&")" | K20: ="Año 9 ("&TEXT(Demanda!$C$2+(4),"0")&")" | L20: ="Año 10 ("&TEXT(Demanda!$C$2+(5),"0")&")"
B21: =Precios!B8 | G21: =IFERROR(ROUND(G8*$C$4,2),"") | H21: =IFERROR(ROUND(H8*$C$4,2),"") | I21: =IFERROR(ROUND(I8*$C$4,2),"") | J21: =IFERROR(ROUND(J8*$C$4,2),"") | K21: =IFERROR(ROUND(K8*$C$4,2),"") | L21: =IFERROR(ROUND(L8*$C$4,2),"")
B22: =Precios!B9 | G22: =IFERROR(ROUND(G9*$C$4,2),"") | H22: =IFERROR(ROUND(H9*$C$4,2),"") | I22: =IFERROR(ROUND(I9*$C$4,2),"") | J22: =IFERROR(ROUND(J9*$C$4,2),"") | K22: =IFERROR(ROUND(K9*$C$4,2),"") | L22: =IFERROR(ROUND(L9*$C$4,2),"")
B23: =Precios!B10 | G23: =IFERROR(ROUND(G10*$C$4,2),"") | H23: =IFERROR(ROUND(H10*$C$4,2),"") | I23: =IFERROR(ROUND(I10*$C$4,2),"") | J23: =IFERROR(ROUND(J10*$C$4,2),"") | K23: =IFERROR(ROUND(K10*$C$4,2),"") | L23: =IFERROR(ROUND(L10*$C$4,2),"")
B24: =Precios!B11 | G24: =IFERROR(ROUND(G11*$C$4,2),"") | H24: =IFERROR(ROUND(H11*$C$4,2),"") | I24: =IFERROR(ROUND(I11*$C$4,2),"") | J24: =IFERROR(ROUND(J11*$C$4,2),"") | K24: =IFERROR(ROUND(K11*$C$4,2),"") | L24: =IFERROR(ROUND(L11*$C$4,2),"")
B25: =Precios!B12 | G25: =IFERROR(ROUND(G12*$C$4,2),"") | H25: =IFERROR(ROUND(H12*$C$4,2),"") | I25: =IFERROR(ROUND(I12*$C$4,2),"") | J25: =IFERROR(ROUND(J12*$C$4,2),"") | K25: =IFERROR(ROUND(K12*$C$4,2),"") | L25: =IFERROR(ROUND(L12*$C$4,2),"")
B26: =Precios!B13 | G26: =IFERROR(ROUND(G13*$C$4,2),"") | H26: =IFERROR(ROUND(H13*$C$4,2),"") | I26: =IFERROR(ROUND(I13*$C$4,2),"") | J26: =IFERROR(ROUND(J13*$C$4,2),"") | K26: =IFERROR(ROUND(K13*$C$4,2),"") | L26: =IFERROR(ROUND(L13*$C$4,2),"")
B27: =Precios!B14 | G27: =IFERROR(ROUND(G14*$C$4,2),"") | H27: =IFERROR(ROUND(H14*$C$4,2),"") | I27: =IFERROR(ROUND(I14*$C$4,2),"") | J27: =IFERROR(ROUND(J14*$C$4,2),"") | K27: =IFERROR(ROUND(K14*$C$4,2),"") | L27: =IFERROR(ROUND(L14*$C$4,2),"")
B28: =Precios!B15 | G28: =IFERROR(ROUND(G15*$C$4,2),"") | H28: =IFERROR(ROUND(H15*$C$4,2),"") | I28: =IFERROR(ROUND(I15*$C$4,2),"") | J28: =IFERROR(ROUND(J15*$C$4,2),"") | K28: =IFERROR(ROUND(K15*$C$4,2),"") | L28: =IFERROR(ROUND(L15*$C$4,2),"")
B29: =Precios!B16 | G29: =IFERROR(ROUND(G16*$C$4,2),"") | H29: =IFERROR(ROUND(H16*$C$4,2),"") | I29: =IFERROR(ROUND(I16*$C$4,2),"") | J29: =IFERROR(ROUND(J16*$C$4,2),"") | K29: =IFERROR(ROUND(K16*$C$4,2),"") | L29: =IFERROR(ROUND(L16*$C$4,2),"")
B30: =Precios!B17 | G30: =IFERROR(ROUND(G17*$C$4,2),"") | H30: =IFERROR(ROUND(H17*$C$4,2),"") | I30: =IFERROR(ROUND(I17*$C$4,2),"") | J30: =IFERROR(ROUND(J17*$C$4,2),"") | K30: =IFERROR(ROUND(K17*$C$4,2),"") | L30: =IFERROR(ROUND(L17*$C$4,2),"")
B32: C. INGRESO BRUTO PROYECTADO (Precio Facturado × Demanda Objetivo por producto, Bs)
B33: Producto / Servicio | C33: — | H33: ="Año 6 ("&TEXT(Demanda!$C$2+(1),"0")&")" | I33: ="Año 7 ("&TEXT(Demanda!$C$2+(2),"0")&")" | J33: ="Año 8 ("&TEXT(Demanda!$C$2+(3),"0")&")" | K33: ="Año 9 ("&TEXT(Demanda!$C$2+(4),"0")&")" | L33: ="Año 10 ("&TEXT(Demanda!$C$2+(5),"0")&")"
B34: =Precios!B8 | H34: =IFERROR(ROUND(H21*Demanda!H64,2),0) | I34: =IFERROR(ROUND(I21*Demanda!I64,2),0) | J34: =IFERROR(ROUND(J21*Demanda!J64,2),0) | K34: =IFERROR(ROUND(K21*Demanda!K64,2),0) | L34: =IFERROR(ROUND(L21*Demanda!L64,2),0)
B35: =Precios!B9 | H35: =IFERROR(ROUND(H22*Demanda!H65,2),0) | I35: =IFERROR(ROUND(I22*Demanda!I65,2),0) | J35: =IFERROR(ROUND(J22*Demanda!J65,2),0) | K35: =IFERROR(ROUND(K22*Demanda!K65,2),0) | L35: =IFERROR(ROUND(L22*Demanda!L65,2),0)
B36: =Precios!B10 | H36: =IFERROR(ROUND(H23*Demanda!H66,2),0) | I36: =IFERROR(ROUND(I23*Demanda!I66,2),0) | J36: =IFERROR(ROUND(J23*Demanda!J66,2),0) | K36: =IFERROR(ROUND(K23*Demanda!K66,2),0) | L36: =IFERROR(ROUND(L23*Demanda!L66,2),0)
B37: =Precios!B11 | H37: =IFERROR(ROUND(H24*Demanda!H67,2),0) | I37: =IFERROR(ROUND(I24*Demanda!I67,2),0) | J37: =IFERROR(ROUND(J24*Demanda!J67,2),0) | K37: =IFERROR(ROUND(K24*Demanda!K67,2),0) | L37: =IFERROR(ROUND(L24*Demanda!L67,2),0)
B38: =Precios!B12 | H38: =IFERROR(ROUND(H25*Demanda!H68,2),0) | I38: =IFERROR(ROUND(I25*Demanda!I68,2),0) | J38: =IFERROR(ROUND(J25*Demanda!J68,2),0) | K38: =IFERROR(ROUND(K25*Demanda!K68,2),0) | L38: =IFERROR(ROUND(L25*Demanda!L68,2),0)
B39: =Precios!B13 | H39: =IFERROR(ROUND(H26*Demanda!H69,2),0) | I39: =IFERROR(ROUND(I26*Demanda!I69,2),0) | J39: =IFERROR(ROUND(J26*Demanda!J69,2),0) | K39: =IFERROR(ROUND(K26*Demanda!K69,2),0) | L39: =IFERROR(ROUND(L26*Demanda!L69,2),0)
B40: =Precios!B14 | H40: =IFERROR(ROUND(H27*Demanda!H70,2),0) | I40: =IFERROR(ROUND(I27*Demanda!I70,2),0) | J40: =IFERROR(ROUND(J27*Demanda!J70,2),0) | K40: =IFERROR(ROUND(K27*Demanda!K70,2),0) | L40: =IFERROR(ROUND(L27*Demanda!L70,2),0)
B41: =Precios!B15 | H41: =IFERROR(ROUND(H28*Demanda!H71,2),0) | I41: =IFERROR(ROUND(I28*Demanda!I71,2),0) | J41: =IFERROR(ROUND(J28*Demanda!J71,2),0) | K41: =IFERROR(ROUND(K28*Demanda!K71,2),0) | L41: =IFERROR(ROUND(L28*Demanda!L71,2),0)
B42: =Precios!B16 | H42: =IFERROR(ROUND(H29*Demanda!H72,2),0) | I42: =IFERROR(ROUND(I29*Demanda!I72,2),0) | J42: =IFERROR(ROUND(J29*Demanda!J72,2),0) | K42: =IFERROR(ROUND(K29*Demanda!K72,2),0) | L42: =IFERROR(ROUND(L29*Demanda!L72,2),0)
B43: =Precios!B17 | H43: =IFERROR(ROUND(H30*Demanda!H73,2),0) | I43: =IFERROR(ROUND(I30*Demanda!I73,2),0) | J43: =IFERROR(ROUND(J30*Demanda!J73,2),0) | K43: =IFERROR(ROUND(K30*Demanda!K73,2),0) | L43: =IFERROR(ROUND(L30*Demanda!L73,2),0)
B44: TOTAL INGRESO BRUTO (Bs) | H44: =IFERROR(SUM(H34:H43),0) | I44: =IFERROR(SUM(I34:I43),0) | J44: =IFERROR(SUM(J34:J43),0) | K44: =IFERROR(SUM(K34:K43),0) | L44: =IFERROR(SUM(L34:L43),0)
B46: LEYENDA: 🟡 Amarillo = parámetros INPUT 🟠 Naranja = precio base a ingresar 🟢 Verde = cálculo automático ⬛ Gris = no aplica para esa sección
